pastebin_replace/__init__.py
pastebin_replace/__main__.py
pastebin_replace-0.1.1.dist-info/METADATA
pastebin_replace-0.1.1.dist-info/WHEEL
pastebin_replace-0.1.1.dist-info/entry_points.txt
pastebin_replace-0.1.1.dist-info/licenses/LICENSE
pastebin_replace-0.1.1.dist-info/RECORD
