Metadata-Version: 2.1
Name: pastebin-replace
Version: 0.1.1
Summary: Replace local files with code from a pastebin link
Project-URL: Homepage, https://github.com/etherealxx/pastebin-replace
Project-URL: Issues, https://github.com/etherealxx/pastebin-replace/issues
Author-email: Etherealxx <gwathon3@gmail.com>
License-File: LICENSE
Keywords: development,download,pastebin,productivity
Classifier: Environment :: Console
Classifier: License :: OSI Approved :: MIT License
Classifier: Operating System :: OS Independent
Classifier: Programming Language :: Python :: 3
Classifier: Topic :: Software Development :: Libraries :: Python Modules
Requires-Python: >=3.8
Requires-Dist: click
Requires-Dist: requests
